zengin_code/__init__.py
zengin_code/bank.py
zengin_code/branch.py
zengin_code/source-data/data/banks.json
zengin_code/source-data/data/md5
zengin_code/source-data/data/updated_at
zengin_code/source-data/data/branches/0001.json
zengin_code/source-data/data/branches/0005.json
zengin_code/source-data/data/branches/0009.json
zengin_code/source-data/data/branches/0010.json
zengin_code/source-data/data/branches/0017.json
zengin_code/source-data/data/branches/0033.json
zengin_code/source-data/data/branches/0034.json
zengin_code/source-data/data/branches/0035.json
zengin_code/source-data/data/branches/0036.json
zengin_code/source-data/data/branches/0038.json
zengin_code/source-data/data/branches/0039.json
zengin_code/source-data/data/branches/0040.json
zengin_code/source-data/data/branches/0041.json
zengin_code/source-data/data/branches/0042.json
zengin_code/source-data/data/branches/0043.json
zengin_code/source-data/data/branches/0044.json
zengin_code/source-data/data/branches/0116.json
zengin_code/source-data/data/branches/0117.json
zengin_code/source-data/data/branches/0118.json
zengin_code/source-data/data/branches/0119.json
zengin_code/source-data/data/branches/0120.json
zengin_code/source-data/data/branches/0121.json
zengin_code/source-data/data/branches/0122.json
zengin_code/source-data/data/branches/0123.json
zengin_code/source-data/data/branches/0124.json
zengin_code/source-data/data/branches/0125.json
zengin_code/source-data/data/branches/0126.json
zengin_code/source-data/data/branches/0128.json
zengin_code/source-data/data/branches/0129.json
zengin_code/source-data/data/branches/0130.json
zengin_code/source-data/data/branches/0131.json
zengin_code/source-data/data/branches/0133.json
zengin_code/source-data/data/branches/0134.json
zengin_code/source-data/data/branches/0135.json
zengin_code/source-data/data/branches/0137.json
zengin_code/source-data/data/branches/0138.json
zengin_code/source-data/data/branches/0140.json
zengin_code-1.1.0.20251215.dist-info/licenses/LICENSE.txt
zengin_code-1.1.0.20251215.dist-info/METADATA
zengin_code-1.1.0.20251215.dist-info/WHEEL
zengin_code-1.1.0.20251215.dist-info/top_level.txt
zengin_code-1.1.0.20251215.dist-info/RECORD
